{"vocabularies": [{"vocabulary": "trend", "partOfSpeech": "n.", "chinese": "時尚、新款式；趨勢"}, {"vocabulary": "trend", "partOfSpeech": "v.", "chinese": "在網路或社群媒體備受注目"}, {"vocabulary": "bold", "partOfSpeech": "adj.", "chinese": "色彩醒目、鮮明的；顯著的"}, {"vocabulary": "bitter", "partOfSpeech": "adj.", "chinese": "極為不滿的；怨恨的"}, {"vocabulary": "annoying", "partOfSpeech": "adj.", "chinese": "惱人的；令人厭煩的"}, {"vocabulary": "suggestion", "partOfSpeech": "n.", "chinese": "建議、提議"}, {"vocabulary": "lean", "partOfSpeech": "v.", "chinese": "傾向於；傾斜"}, {"vocabulary": "addicted", "partOfSpeech": "adj.", "chinese": "入迷的；上癮的"}, {"vocabulary": "diverse", "partOfSpeech": "adj.", "chinese": "多樣化的；各式各樣的"}]}